maat.cpython-310-darwin.so
pymaat.dylibs/libgmp.10.dylib
maat/share/processors/EVM.pspec
maat/share/processors/EVM.sla
maat/share/processors/x86.pspec
maat/share/processors/x86-64.pspec
maat/share/processors/x86-64.sla
maat/share/processors/x86.sla
pymaat-0.6.9.dist-info/RECORD
pymaat-0.6.9.dist-info/WHEEL
pymaat-0.6.9.dist-info/top_level.txt
pymaat-0.6.9.dist-info/METADATA
