Metadata-Version: 2.1
Name: pymaat
Version: 0.6.9
Summary: Maat - Symbolic execution framework
Home-page: https://maat.re
License: LGPL
Project-URL: Changelog, https://github.com/trailofbits/maat/releases
Project-URL: Tracker, https://github.com/trailofbits/issues
Project-URL: Documentation, https://maat.re
Project-URL: Source, https://github.com/trailofbits/maat
Keywords: maat,symbolic,emulation,concolic,binary analysis,pcode
Classifier: Development Status :: 4 - Beta
Classifier: Operating System :: POSIX :: Linux
Classifier: Operating System :: MacOS
Classifier: Intended Audience :: Science/Research
Classifier: Programming Language :: C++
Classifier: Programming Language :: Python :: Implementation :: CPython
Classifier: License :: OSI Approved :: GNU Lesser General Public License v2 or later (LGPLv2+)
Requires-Python: >=3.7
